wavecar2unk.py
wavecar2unk-0.0.2.dist-info/LICENSE
wavecar2unk-0.0.2.dist-info/METADATA
wavecar2unk-0.0.2.dist-info/WHEEL
wavecar2unk-0.0.2.dist-info/entry_points.txt
wavecar2unk-0.0.2.dist-info/top_level.txt
wavecar2unk-0.0.2.dist-info/RECORD
