Metadata-Version: 2.1
Name: wavecar2unk
Version: 0.0.2
Summary: converts VASP WAVECAR file into UNK files for wannier90
Home-page: https://github.com/mturiansky/wavecar2unk
Author: Mark E. Turiansky
Author-email: mturiansky@physics.ucsb.edu
License: UNKNOWN
Keywords: physics,materials,science,VASP,WAVECAR,wannier90
Platform: UNKNOWN
Classifier: Programming Language :: Python :: 3
Classifier: License :: OSI Approved :: MIT License
Classifier: Operating System :: OS Independent
Requires-Dist: pymatgen (>2020.4.29)
Requires-Dist: click (>=7.1.2)
